Metadata-Version: 2.1
Name: aiida-supercell
Version: 1.0.1
Summary: AiiDA Plugin for Supercell program
Home-page: https://github.com/pzarabadip/aiida-supercell
Author: Pezhman Zarabadi-Poor
Author-email: pzarabadip@gmail.com
License: MIT License
Classifier: Programming Language :: Python :: 3.8
Classifier: Programming Language :: Python :: 3.9
Provides-Extra: testing
Provides-Extra: pre-commit
Provides-Extra: docs
License-File: LICENSE
